ELKLogging/__init__.py
ELKLogging/Formatter/BaseFormatter.py
ELKLogging/Formatter/FileFormatter.py
ELKLogging/Formatter/LogstashFormatter.py
ELKLogging/Formatter/StreamFormatter.py
ELKLogging/Formatter/__init__.py
ELKLogging/Handler/BaseHandler.py
ELKLogging/Handler/FileHandler.py
ELKLogging/Handler/LogstashHandler.py
ELKLogging/Handler/StreamHandler.py
ELKLogging/Handler/__init__.py
ELKLogging/Infra/Enum.py
ELKLogging/Infra/Singletone.py
ELKLogging/Infra/SystemMetricsCatcher.py
ELKLogging/Infra/__init__.py
ELKLogging-0.1.4.dist-info/METADATA
ELKLogging-0.1.4.dist-info/WHEEL
ELKLogging-0.1.4.dist-info/top_level.txt
ELKLogging-0.1.4.dist-info/RECORD
